h11pro/__init__.py
h11pro/_abnf.py
h11pro/_connection.py
h11pro/_events.py
h11pro/_headers.py
h11pro/_readers.py
h11pro/_receivebuffer.py
h11pro/_state.py
h11pro/_util.py
h11pro/_version.py
h11pro/_writers.py
h11pro/py.typed
h11pro/tests/__init__.py
h11pro/tests/helpers.py
h11pro/tests/test_against_stdlib_http.py
h11pro/tests/test_connection.py
h11pro/tests/test_events.py
h11pro/tests/test_headers.py
h11pro/tests/test_helpers.py
h11pro/tests/test_io.py
h11pro/tests/test_receivebuffer.py
h11pro/tests/test_state.py
h11pro/tests/test_util.py
h11pro-0.0.1.dist-info/licenses/LICENSE.txt
h11pro-0.0.1.dist-info/METADATA
h11pro-0.0.1.dist-info/WHEEL
h11pro-0.0.1.dist-info/top_level.txt
h11pro-0.0.1.dist-info/RECORD
